cassandra_reaper_cli/__about__.py
cassandra_reaper_cli/__init__.py
cassandra_reaper_cli-0.0.1.dist-info/METADATA
cassandra_reaper_cli-0.0.1.dist-info/WHEEL
cassandra_reaper_cli-0.0.1.dist-info/entry_points.txt
cassandra_reaper_cli-0.0.1.dist-info/licenses/LICENSE
cassandra_reaper_cli-0.0.1.dist-info/RECORD
