Metadata-Version: 2.1
Name: cassandra-reaper-cli
Version: 0.0.1
Project-URL: Documentation, https://github.com/evolution-gaming/cassandra-reaper-cli#readme
Project-URL: Issues, https://github.com/evolution-gaming/cassandra-reaper-cli/issues
Project-URL: Source, https://github.com/evolution-gaming/cassandra-reaper-cli
Author-email: Timur Isanov <tisanov@evolution.com>
License-Expression: MIT
License-File: LICENSE
Classifier: Development Status :: 4 - Beta
Classifier: Programming Language :: Python
Classifier: Programming Language :: Python :: 3.7
Classifier: Programming Language :: Python :: 3.8
Classifier: Programming Language :: Python :: 3.9
Classifier: Programming Language :: Python :: 3.10
Classifier: Programming Language :: Python :: 3.11
Classifier: Programming Language :: Python :: Implementation :: CPython
Classifier: Programming Language :: Python :: Implementation :: PyPy
Requires-Python: >=3.7
Requires-Dist: cassandra-reaper-api~=0.0.1
Requires-Dist: shtab~=1.4.2
